MANIFEST.in
setup.py
fbcp/CMakeLists.txt
fbcp/README.md
fbcp/main.c
fbcp/build/empty.txt
icons/cameraA.png
icons/cameraM.png
icons/cameraT.png
icons/cameraV.png
icons/record.png
scificam/ButtonThread.py
scificam/Mode.py
scificam/OwnCloudThread.py
scificam/SciFiCam.py
scificam/__init__.py
scificam/scificam
scificam.egg-info/PKG-INFO
scificam.egg-info/SOURCES.txt
scificam.egg-info/dependency_links.txt
scificam.egg-info/requires.txt
scificam.egg-info/top_level.txt