Metadata-Version: 1.1
Name: scificam
Version: 0.1.1
Summary: Firmware for SciFiCam
Home-page: https://github.com/BioMakers/28_Sci-Fi-Cam
Author: Mihails Delmans
Author-email: m.delmans@gmail.com
License: UNKNOWN
Download-URL: https://github.com/BioMakers/28_Sci-Fi-Cam/archive/0.1.1.tar.gz
Keywords: Raspberry,camera
Platform: UNKNOWN
